bceinternalsdk/__init__.py
bceinternalsdk/client/__init__.py
bceinternalsdk/client/base_model.py
bceinternalsdk/client/bce_internal_client.py
bceinternalsdk/client/decorator.py
bceinternalsdk/client/paging.py
bceinternalsdk/client/test_paging.py
bceinternalsdk/client/validator.py
bce_internal_sdk-1.0.0.12.dist-info/METADATA
bce_internal_sdk-1.0.0.12.dist-info/WHEEL
bce_internal_sdk-1.0.0.12.dist-info/top_level.txt
bce_internal_sdk-1.0.0.12.dist-info/RECORD
