Metadata-Version: 2.1
Name: bce-internal-sdk
Version: 1.0.0.12
Summary: sdk in python for bce internal
Home-page: https://console.cloud.baidu-int.com/devops/icode/repos/baidu/themis/server-python/tree/master
Author: yangtingyu01
Author-email: yangtingyu01@baidu.com
License: MIT
Classifier: Programming Language :: Python
Classifier: Programming Language :: Python :: 3
Classifier: Programming Language :: Python :: 3.7
Classifier: Programming Language :: Python :: 3.8
Classifier: Programming Language :: Python :: 3.9
Requires-Python: >=3.6
Requires-Dist: bce-python-sdk (==0.8.87)
Requires-Dist: click (==8.1.7)
